src/cli.py
src/logic.py
starknet_interface_generator/__init__.py
starknet_interface_generator/generator.py
starknet_interface_generator/interface_parser.py
starknet_interface_generator/utils.py
starknet_interface_generator-0.1.5.dist-info/entry_points.txt
starknet_interface_generator-0.1.5.dist-info/LICENSE
starknet_interface_generator-0.1.5.dist-info/WHEEL
starknet_interface_generator-0.1.5.dist-info/METADATA
starknet_interface_generator-0.1.5.dist-info/RECORD
